{
  "subject": "english",
  "subjectName": "英語",
  "category": "phonetic-symbols-fricatives",
  "categoryName": "🔊 摩擦音",
  "topCategory": "pronunciation",
  "topCategoryName": "発音",
  "parentCategory": "phonetic-symbols",
  "parentCategoryName": "発音記号",
  "guideUrl": "./english/pronunciation/phonetic-symbols/fricatives/guide",
  "parentCategoryGuideUrl": "./english/pronunciation/guide",
  "example": "/θ/→ス（think）",
  "referenceGrade": "中学1年",
  "description": "息を擦って出す摩擦音の発音記号（IPA）9種を学びます。",
  "questions": [
    {
      "id": "f73e749b-c462-54c8-8b39-7b63eb3c0adc",
      "question": "/f/ はどんな音？",
      "choices": [
        "上の歯を下唇に当てる無声摩擦音",
        "上の歯を下唇に当てる有声摩擦音",
        "唇を閉じて開く無声破裂音",
        "舌先を上の歯に当てる無声音"
      ],
      "correct": 0,
      "explanation": "/f/ は上の歯を下唇に軽く当てて息を出す無声摩擦音。fan, off, leaf などに使われる。/v/ の無声バージョン。"
    },
    {
      "id": "1e4659da-1e75-525e-9643-651b8287de0d",
      "question": "/v/ はどんな音？",
      "choices": [
        "上の歯を下唇に当てる有声摩擦音",
        "上の歯を下唇に当てる無声摩擦音",
        "唇を閉じて開く有声破裂音",
        "舌先を上の歯に当てる有声音"
      ],
      "correct": 0,
      "explanation": "/v/ は上の歯を下唇に当てて声を出す有声摩擦音。van, love, give などに使われる。/f/ の有声バージョン。"
    },
    {
      "id": "85774167-02ad-5bca-893a-fcb58963dc78",
      "question": "/θ/ はどんな音？",
      "choices": [
        "舌先を上の歯に当てる無声摩擦音（「ス」に近い）",
        "舌先を上の歯に当てる有声摩擦音（「ズ」に近い）",
        "「シュ」の音",
        "舌先を歯茎に当てる無声破裂音"
      ],
      "correct": 0,
      "explanation": "/θ/ は舌先を上の歯に軽く当てて息を出す無声摩擦音。think, three, tooth などに使われる。/ð/ の無声バージョン。"
    },
    {
      "id": "05e29ad2-d37f-5568-9f9f-beb0771b8981",
      "question": "/ð/ はどんな音？",
      "choices": [
        "舌先を上の歯に当てる有声摩擦音（「ズ」に近い）",
        "舌先を上の歯に当てる無声摩擦音（「ス」に近い）",
        "「ジュ」の破裂音",
        "「シュ」の音"
      ],
      "correct": 0,
      "explanation": "/ð/ は /θ/ と同じ舌の動きで声を出す有声摩擦音。this, that, the などに使われる。/θ/ の有声バージョン。"
    },
    {
      "id": "43eae487-b14a-519f-b63d-64b3806cc3fa",
      "question": "/s/ はどんな音？",
      "choices": ["「ス」（無声摩擦音）", "「ズ」（有声摩擦音）", "「シュ」（無声摩擦音）", "「ジュ」（有声摩擦音）"],
      "correct": 0,
      "explanation": "/s/ は「ス」の無声摩擦音。see, bus, pass などに使われる。/z/ の無声バージョン。"
    },
    {
      "id": "0463e9fa-4ba5-5f67-a66a-3c53e10c8f4f",
      "question": "/z/ はどんな音？",
      "choices": ["「ズ」（有声摩擦音）", "「ス」（無声摩擦音）", "「ジュ」（有声摩擦音）", "「シュ」（無声摩擦音）"],
      "correct": 0,
      "explanation": "/z/ は「ズ」の有声摩擦音。zoo, buzz, nose などに使われる。/s/ の有声バージョン。"
    },
    {
      "id": "5940be57-addf-564d-8b6e-1a11d67ea8af",
      "question": "/ʃ/ はどんな音？",
      "choices": ["「シュ」（無声摩擦音）", "「チュ」（無声破擦音）", "「ジュ」（有声摩擦音）", "「ス」（無声摩擦音）"],
      "correct": 0,
      "explanation": "/ʃ/ は「シュ」の無声摩擦音。she, shoe, wish などに使われる。/ʒ/ の無声バージョン。"
    },
    {
      "id": "3ae407dd-374b-58ea-8e05-9253e4552dcd",
      "question": "/ʒ/ はどんな音？",
      "choices": [
        "「ジュ」（有声摩擦音、濁った「シュ」）",
        "「シュ」（無声摩擦音）",
        "「チュ」（無声破擦音）",
        "「ジュ」（有声破擦音）"
      ],
      "correct": 0,
      "explanation": "/ʒ/ は /ʃ/ を濁らせた「ジュ」の有声摩擦音。vision, measure, television などに使われる。/ʃ/ の有声バージョン。"
    },
    {
      "id": "892dba8b-70b2-51ea-89af-9db94d79a103",
      "question": "/h/ はどんな音？",
      "choices": [
        "息だけを出す無声摩擦音（「ハ」行）",
        "唇を閉じて開く無声破裂音",
        "舌先を上の歯に当てる無声音",
        "「シュ」の音"
      ],
      "correct": 0,
      "explanation": "/h/ は息だけを出す無声摩擦音。he, hat, behind などに使われる。日本語の「ハ行」に近いが、より息を多く使う。"
    }
  ]
}
