{
  "subject": "math",
  "subjectName": "数学",
  "category": "division-remainder-2digit",
  "categoryName": "➗ ２桁・あまりあり",
  "topCategory": "arithmetic",
  "topCategoryName": "算数・基本計算",
  "parentCategory": "division",
  "parentCategoryName": "わり算",
  "guideUrl": "../math/arithmetic/division-2digit-remainder/guide",
  "parentCategoryGuideUrl": "../math/arithmetic/guide",
  "example": "85 ÷ 12 = 7…1",
  "referenceGrade": "小学3年",
  "description": "あまりのある2けたのわり算を正確に計算できるようにします。",
  "questions": [
    {
      "id": "541f930f-a503-53f0-a109-9c6878a34384",
      "question": "27 ÷ 4 = ? あまり ?",
      "choices": [
        "6 あまり 3",
        "6 あまり 4",
        "7 あまり 3",
        "5 あまり 4"
      ],
      "correct": 0,
      "explanation": "4 × 6 = 24。27 - 24 = 3。答え 6 あまり 3"
    },
    {
      "id": "d678d232-6f58-5bcf-b916-c3e975e03ff0",
      "question": "35 ÷ 6 = ? あまり ?",
      "choices": [
        "5 あまり 5",
        "5 あまり 6",
        "6 あまり 5",
        "4 あまり 6"
      ],
      "correct": 0,
      "explanation": "6 × 5 = 30。35 - 30 = 5。答え 5 あまり 5"
    },
    {
      "id": "462c6590-1b71-5cf0-a44e-a31463f2e92d",
      "question": "43 ÷ 7 = ? あまり ?",
      "choices": [
        "6 あまり 1",
        "6 あまり 2",
        "7 あまり 1",
        "5 あまり 2"
      ],
      "correct": 0,
      "explanation": "7 × 6 = 42。43 - 42 = 1。答え 6 あまり 1"
    },
    {
      "id": "16b20746-032d-527f-85cd-e5e1b6ad3868",
      "question": "50 ÷ 8 = ? あまり ?",
      "choices": [
        "6 あまり 2",
        "6 あまり 3",
        "7 あまり 2",
        "5 あまり 3"
      ],
      "correct": 0,
      "explanation": "8 × 6 = 48。50 - 48 = 2。答え 6 あまり 2"
    },
    {
      "id": "b9fab5a2-f35a-57aa-af85-cdf63fd54132",
      "question": "37 ÷ 5 = ? あまり ?",
      "choices": [
        "7 あまり 2",
        "7 あまり 3",
        "8 あまり 2",
        "6 あまり 3"
      ],
      "correct": 0,
      "explanation": "5 × 7 = 35。37 - 35 = 2。答え 7 あまり 2"
    },
    {
      "id": "6f2a7901-fba1-54a9-bd80-044109552ee9",
      "question": "53 ÷ 6 = ? あまり ?",
      "choices": [
        "8 あまり 5",
        "8 あまり 6",
        "9 あまり 5",
        "7 あまり 6"
      ],
      "correct": 0,
      "explanation": "6 × 8 = 48。53 - 48 = 5。答え 8 あまり 5"
    },
    {
      "id": "277e0847-400c-56d6-b8e9-433a1519d1a0",
      "question": "67 ÷ 9 = ? あまり ?",
      "choices": [
        "7 あまり 4",
        "7 あまり 5",
        "8 あまり 4",
        "6 あまり 5"
      ],
      "correct": 0,
      "explanation": "9 × 7 = 63。67 - 63 = 4。答え 7 あまり 4"
    },
    {
      "id": "5516437b-ca05-5945-8ba5-e2f4016b7c00",
      "question": "45 ÷ 7 = ? あまり ?",
      "choices": [
        "6 あまり 3",
        "6 あまり 4",
        "7 あまり 3",
        "5 あまり 4"
      ],
      "correct": 0,
      "explanation": "7 × 6 = 42。45 - 42 = 3。答え 6 あまり 3"
    },
    {
      "id": "b5e4b2aa-02f3-5116-9c00-4a8b0a39edfe",
      "question": "58 ÷ 9 = ? あまり ?",
      "choices": [
        "6 あまり 4",
        "6 あまり 5",
        "7 あまり 4",
        "5 あまり 5"
      ],
      "correct": 0,
      "explanation": "9 × 6 = 54。58 - 54 = 4。答え 6 あまり 4"
    },
    {
      "id": "ec62cf2c-c3e4-533b-a5b1-3c9722480c70",
      "question": "47 ÷ 6 = ? あまり ?",
      "choices": [
        "7 あまり 5",
        "7 あまり 6",
        "8 あまり 5",
        "6 あまり 6"
      ],
      "correct": 0,
      "explanation": "6 × 7 = 42。47 - 42 = 5。答え 7 あまり 5"
    },
    {
      "id": "01b3d7e6-d01c-585b-8290-de16d42ec946",
      "question": "62 ÷ 8 = ? あまり ?",
      "choices": [
        "7 あまり 6",
        "7 あまり 7",
        "8 あまり 6",
        "6 あまり 7"
      ],
      "correct": 0,
      "explanation": "8 × 7 = 56。62 - 56 = 6。答え 7 あまり 6"
    },
    {
      "id": "a07e233c-52ca-5742-9ab9-1822049de73c",
      "question": "74 ÷ 9 = ? あまり ?",
      "choices": [
        "8 あまり 2",
        "8 あまり 3",
        "9 あまり 2",
        "7 あまり 3"
      ],
      "correct": 0,
      "explanation": "9 × 8 = 72。74 - 72 = 2。答え 8 あまり 2"
    },
    {
      "id": "34a463a4-754d-55c2-883a-2912a03d7727",
      "question": "33 ÷ 4 = ? あまり ?",
      "choices": [
        "8 あまり 1",
        "8 あまり 2",
        "9 あまり 1",
        "7 あまり 2"
      ],
      "correct": 0,
      "explanation": "4 × 8 = 32。33 - 32 = 1。答え 8 あまり 1"
    },
    {
      "id": "c5489d84-f520-5dcb-8865-4690a29f7d38",
      "question": "41 ÷ 6 = ? あまり ?",
      "choices": [
        "6 あまり 5",
        "6 あまり 6",
        "7 あまり 5",
        "5 あまり 6"
      ],
      "correct": 0,
      "explanation": "6 × 6 = 36。41 - 36 = 5。答え 6 あまり 5"
    },
    {
      "id": "3066d83a-1f7b-5aa2-8b4f-83d27d26c14a",
      "question": "55 ÷ 7 = ? あまり ?",
      "choices": [
        "7 あまり 6",
        "7 あまり 7",
        "8 あまり 6",
        "6 あまり 7"
      ],
      "correct": 0,
      "explanation": "7 × 7 = 49。55 - 49 = 6。答え 7 あまり 6"
    }
  ]
}
